[
  {
    "year": 2008,
    "NL": "511,569",
    "PE": "138,736",
    "NS": "935,965",
    "NB": "746,875",
    "QC": "7,761,614",
    "ON": "12,883,824",
    "MB": "1,197,767",
    "SK": "1,017,368",
    "AB": "3,595,875",
    "BC": 4349338
  },
  {
    "year": 2009,
    "NL": "516,741",
    "PE": "139,873",
    "NS": "938,266",
    "NB": "749,956",
    "QC": "7,843,915",
    "ON": "12,998,941",
    "MB": "1,208,555",
    "SK": "1,034,791",
    "AB": "3,679,010",
    "BC": 4410513
  },
  {
    "year": 2010,
    "NL": "522,002",
    "PE": "141,644",
    "NS": "942,144",
    "NB": "753,034",
    "QC": "7,929,479",
    "ON": "13,136,481",
    "MB": "1,220,782",
    "SK": "1,051,426",
    "AB": "3,732,104",
    "BC": 4465557
  },
  {
    "year": 2011,
    "NL": "524,955",
    "PE": "143,918",
    "NS": "944,095",
    "NB": "755,590",
    "QC": "8,004,736",
    "ON": "13,262,345",
    "MB": "1,233,353",
    "SK": "1,065,661",
    "AB": "3,787,705",
    "BC": 4503819
  },
  {
    "year": 2012,
    "NL": 526235,
    "PE": 144415,
    "NS": 943163,
    "NB": 758121,
    "QC": 8059752,
    "ON": 13392364,
    "MB": 1249094,
    "SK": 1083005,
    "AB": 3871947,
    "BC": 4570866
  },
  {
    "year": 2013,
    "NL": 526960,
    "PE": 143942,
    "NS": 939808,
    "NB": 758261,
    "QC": 8108825,
    "ON": 13511902,
    "MB": 1263393,
    "SK": 1098868,
    "AB": 3978532,
    "BC": 4634943
  },
  {
    "year": 2014,
    "NL": 527970,
    "PE": 144095,
    "NS": 937768,
    "NB": 758657,
    "QC": 8147535,
    "ON": 13617763,
    "MB": 1277425,
    "SK": 1111989,
    "AB": 4081271,
    "BC": 4712691
  },
  {
    "year": 2015,
    "NL": 528348,
    "PE": 144636,
    "NS": 937419,
    "NB": 759226,
    "QC": 8175743,
    "ON": 13709293,
    "MB": 1293598,
    "SK": 1122210,
    "AB": 4150147,
    "BC": 4765472
  },
  {
    "year": 2016,
    "NL": 529586,
    "PE": 146891,
    "NS": 942984,
    "NB": 763322,
    "QC": 8225036,
    "ON": 13876500,
    "MB": 1314140,
    "SK": 1135496,
    "AB": 4195427,
    "BC": 4861269
  },
  {
    "year": 2017,
    "NL": 529742,
    "PE": 149740,
    "NS": 952159,
    "NB": 766697,
    "QC": 8292832,
    "ON": 14078499,
    "MB": 1334734,
    "SK": 1147315,
    "AB": 4237310,
    "BC": 4934202
  },
  {
    "year": 2018,
    "NL": 528402,
    "PE": 152259,
    "NS": 962072,
    "NB": 770497,
    "QC": 8386951,
    "ON": 14326746,
    "MB": 1352687,
    "SK": 1156210,
    "AB": 4292556,
    "BC": 5020979
  },
  {
    "year": 2019,
    "NL": 527643,
    "PE": 155792,
    "NS": 975799,
    "NB": 777387,
    "QC": 8483186,
    "ON": 14573565,
    "MB": 1370033,
    "SK": 1164223,
    "AB": 4355377,
    "BC": 5111022
  },
  {
    "year": 2020,
    "NL": 526884,
    "PE": 159193,
    "NS": 989168,
    "NB": 783432,
    "QC": 8551095,
    "ON": 14761811,
    "MB": 1380132,
    "SK": 1167386,
    "AB": 4407495,
    "BC": 5176101
  },
  {
    "year": 2021,
    "NL": 527056,
    "PE": 162133,
    "NS": 999908,
    "NB": 790802,
    "QC": 8572020,
    "ON": 14842488,
    "MB": 1391924,
    "SK": 1167711,
    "AB": 4431531,
    "BC": 5226665
  },
  {
    "year": 2022,
    "NL": 531257,
    "PE": 167200,
    "NS": 1024034,
    "NB": 808869,
    "QC": 8669963,
    "ON": 15155836,
    "MB": 1413498,
    "SK": 1178796,
    "AB": 4512731,
    "BC": 5358845
  },
  {
    "year": 2023,
    "NL": 538789,
    "PE": 173734,
    "NS": 1053005,
    "NB": 831103,
    "QC": 8821696,
    "ON": 15632481,
    "MB": 1453202,
    "SK": 1210257,
    "AB": 4688576,
    "BC": 5515296
  },
  {
    "year": 2024,
    "NL": 546869,
    "PE": 179709,
    "NS": 1082769,
    "NB": 858293,
    "QC": 8995474,
    "ON": 16144797,
    "MB": 1492144,
    "SK": 1247868,
    "AB": 4909030,
    "BC": 5671114
  },
  {
    "year": 2025,
    "NL": 549911,
    "PE": 182657,
    "NS": 1093245,
    "NB": 869682,
    "QC": 9058297,
    "ON": 16258260,
    "MB": 1509702,
    "SK": 1266959,
    "AB": 5029346,
    "BC": 5697536
  }
]
